<staticSiteGenerators><staticSiteGenerator author="Стивен Кинг" release_year="2014" genre="Ужасы" number_of_pages="384">Зелёная миля</staticSiteGenerator><staticSiteGenerator author="Джоан Роулинг" release_year="2003" genre="Фэнтези" number_of_pages="544">Гарри Поттер и Дары Смерти</staticSiteGenerator><staticSiteGenerator author="Стивен Кинг" release_year="2014" genre="Ужасы" number_of_pages="384">Зелёная миля</staticSiteGenerator><staticSiteGenerator author="Стивен Кинг" release_year="2014" genre="Ужасы" number_of_pages="384">Зелёная миля</staticSiteGenerator><staticSiteGenerator author="Стивен Кинг" release_year="2014" genre="Ужасы" number_of_pages="384">Зелёная миля</staticSiteGenerator><staticSiteGenerator author="Стивен Кинг" release_year="2014" genre="Ужасы" number_of_pages="384">Зелёная миля</staticSiteGenerator><staticSiteGenerator author="Стивен Кинг" release_year="2014" genre="Ужасы" number_of_pages="384">Зелёная миля</staticSiteGenerator><staticSiteGenerator author="Стивен Кинг" release_year="2014" genre="Ужасы" number_of_pages="384">Зелёная миля</staticSiteGenerator><staticSiteGenerator author="Стивен Кинг" release_year="2014" genre="Ужасы" number_of_pages="384">Зелёная миля</staticSiteGenerator><staticSiteGenerator author="Стивен Кинг" release_year="2014" genre="Ужасы" number_of_pages="384">Зелёная миля</staticSiteGenerator></staticSiteGenerators>